setup.py
FightGame/planeGame.py
FightGame.egg-info/PKG-INFO
FightGame.egg-info/SOURCES.txt
FightGame.egg-info/dependency_links.txt
FightGame.egg-info/top_level.txt