Metadata-Version: 2.1
Name: FightGame
Version: 1.0
Summary: pygame写的一个简易飞机大战
Home-page: UNKNOWN
Author: Eno
Author-email: 
License: UNKNOWN
Platform: UNKNOWN
